{
    "yana_qaytdi": "<b>👋 Боз баргаштед!\n\nБот аллакай фаъол аст ✅\n\nБахшро интихоб кунед 👇</b>",
    
    "not_admmin": "Шумо админ нестед 😅",
    
    "bot_news": "📻 ХАБАРҲОИ БОТ",
    
    "oboi": "🌅 ОБОЙҲО",
    
    "help": "<b>🤖 Дар бораи бот\n\n🎨 Ин бот беҳтарин ва зеботарин темаҳоро барои Telegram ҷамъ кардааст.\n\n📂 Дар дохили бот шумо метавонед темаҳоро аз категорияҳои гуногун пайдо кунед:\n\n🖤 Dark — темаҳое бо услуби торик\n\n💖 Anime — дизайнҳои зебо дар услуби аниме\n\n🐯 Ҳайвонот — темаҳое бо расмҳои ҳайвонот\n\n🤍 Soft — темаҳое бо рангҳои мулоим ва гуворо\n\n💔 Дигар — темаҳое ғайриоддӣ ва креативӣ\n\n⚡ Ба бот ҳамеша темаҳое нав илова мешаванд.\n\n📢 Ба канали мо обуна шавед, то аввалин шуда аз темаҳое нав ва хабарҳо огоҳ шавед!</b>",
    
    "platform_choice": "<b>❗ ПЛАТФОРМАРО ИНТИХОБ КУНЕД</b>",
    
    "kat_choice": "<b>🔠 КАТЕГОРИЯРО ИНТИХОБ КУНЕД</b>",
    
    "theme_kat": "ТЕМА\n\nАЗ ТУГМАИ 📲 ИСТИФОДА БАРЕД",
    
    "sekret": "<b>⏳ Ба зудӣ</b>",
    
    "error": "<b>👾 ХАТО 👾\n\n1⃣ ЛУТФАН АЗ ТУГМАҲОИ ПОЁН ИСТИФОДА БАРЕД\n\n2⃣ БО /start БОТРО АЗ НАВ ОҒОЗ КУНЕД</b>",
    
    "rek": "🔥 Инро дигарон пинҳон мекунанд…\n\nСанҷед ва ба дӯстонатон фиристед 😏👇",
    
    "lang_update": "<b>🌍 Забон бомуваффақият иваз шуд!\n\nАкнун бот бо забони интихобкардаи шумо кор мекунад 😊</b>"
}